LensCalcPy/__init__.py
LensCalcPy/_modidx.py
LensCalcPy/core.py
LensCalcPy/ffp.py
LensCalcPy/galaxy.py
LensCalcPy/lens.py
LensCalcPy/lightcurves.py
LensCalcPy/parameters.py
LensCalcPy/pbh.py
LensCalcPy/stats.py
LensCalcPy/survey.py
LensCalcPy/utils.py
LensCalcPy/interpolations/__init__.py
LensCalcPy/interpolations/interps.py
LensCalcPy/interpolations/u_fwhm_interp.pkl
LensCalcPy/interpolations/ut_interp_axion.pkl
LensCalcPy/interpolations/ut_interp_axion_101.pkl
LensCalcPy/interpolations/ut_interp_axion_thresh.pkl
LensCalcPy/interpolations/ut_interp_dressed.pkl
LensCalcPy/interpolations/ut_interp_dressed_101.pkl
LensCalcPy/interpolations/ut_interp_dressed_thresh.pkl
LensCalcPy/interpolations/ut_interp_m31.pkl
LensCalcPy/interpolations/ut_interp_mw.pkl
LensCalcPy/interpolations/ut_interp_nfw.pkl
LensCalcPy/interpolations/ut_interp_nfw_101.pkl
LensCalcPy/interpolations/ut_interp_nfw_thresh.pkl
LensCalcPy/interpolations/ut_interp_rho.pkl
LensCalcPy-0.0.4.dist-info/LICENSE
LensCalcPy-0.0.4.dist-info/METADATA
LensCalcPy-0.0.4.dist-info/WHEEL
LensCalcPy-0.0.4.dist-info/entry_points.txt
LensCalcPy-0.0.4.dist-info/top_level.txt
LensCalcPy-0.0.4.dist-info/RECORD
