Metadata-Version: 2.1
Name: LensCalcPy
Version: 0.0.4
Summary: Calculate Microlensing Observables
Home-page: https://github.com/NolanSmyth/LensCalcPy
Author: Nolan Smyth
Author-email: nolanwsmyth@gmail.com
License: Apache Software License 2.0
Keywords: nbdev jupyter notebook python
Classifier: Development Status :: 4 - Beta
Classifier: Intended Audience :: Developers
Classifier: Natural Language :: English
Classifier: Programming Language :: Python :: 3.7
Classifier: Programming Language :: Python :: 3.8
Classifier: Programming Language :: Python :: 3.9
Classifier: Programming Language :: Python :: 3.10
Classifier: License :: OSI Approved :: Apache Software License
Requires-Python: >=3.7
License-File: LICENSE
Requires-Dist: numpy
Requires-Dist: scipy
Requires-Dist: matplotlib
Requires-Dist: astropy
Requires-Dist: pathos
Requires-Dist: tqdm
Requires-Dist: pandas
Requires-Dist: seaborn
Provides-Extra: dev
